gridmeld/__init__.py
gridmeld/minemeld/__init__.py
gridmeld/minemeld/api.py
gridmeld/pxgrid/__init__.py
gridmeld/pxgrid/rest.py
gridmeld/pxgrid/stomp.py
gridmeld/pxgrid/wsstomp.py
gridmeld/util/__init__.py
gridmeld/util/mixin.py
gridmeld/util/util_daemon.py
gridmeld-0.6.0.data/scripts/gate.py
gridmeld-0.6.0.data/scripts/grid.py
gridmeld-0.6.0.data/scripts/meld.py
gridmeld-0.6.0.dist-info/LICENSE.txt
gridmeld-0.6.0.dist-info/METADATA
gridmeld-0.6.0.dist-info/WHEEL
gridmeld-0.6.0.dist-info/top_level.txt
gridmeld-0.6.0.dist-info/RECORD
