Metadata-Version: 2.1
Name: gridmeld
Version: 0.6.0
Summary: Cisco ISE pxGrid to Palo Alto Networks MineMeld Gateway
Home-page: https://github.com/PaloAltoNetworks/gridmeld
Author: Palo Alto Networks, Inc.
Author-email: techbizdev@paloaltonetworks.com
License: UNKNOWN
Platform: UNKNOWN
Classifier: Development Status :: 3 - Alpha
Classifier: Programming Language :: Python :: 3.6
Classifier: Programming Language :: Python :: 3.7
Classifier: License :: OSI Approved :: Apache Software License
Requires-Dist: aiohttp
Requires-Dist: tenacity
